<?xml version="1.0"?>
<!DOCTYPE hibernate-mapping PUBLIC 
    "-//Hibernate/Hibernate Mapping DTD 3.0//EN"
    "http://hibernate.sourceforge.net/hibernate-mapping-3.0.dtd">

<hibernate-mapping>

    <class dynamic-insert="true" dynamic-update="true" name="nl.strohalm.cyclos.entities.sms.MemberSmsStatus" table="member_sms_status">
        <id name="id" type="long">
		    <column name="id" sql-type="integer"/>
            <generator class="native"/>
        </id>
		<many-to-one name="member" update="false" class="nl.strohalm.cyclos.entities.members.Member">
		    <column name="member_id" sql-type="integer" not-null="true" unique="true" />
		</many-to-one>
		<property name="freeSmsSent" column="free_sms_sent" type="integer" not-null="true" />
		<property name="freeSmsExpiration" column="free_sms_expiration" type="calendar" />
		<property name="paidSmsLeft" column="paid_sms_left" type="integer" not-null="true" />
		<property name="paidSmsExpiration" column="paid_sms_expiration" type="calendar" />
		<property name="allowChargingSms" column="allow_charging_sms" type="boolean" not-null="true" />
		<property name="acceptFreeMailing" column="accept_free_mailing" type="boolean" not-null="true"/>
		<property name="acceptPaidMailing" column="accept_paid_mailing" type="boolean" not-null="true"/>
    </class>

</hibernate-mapping>