<?xml version="1.0"?>
<!DOCTYPE hibernate-mapping PUBLIC 
    "-//Hibernate/Hibernate Mapping DTD 3.0//EN"
    "http://hibernate.sourceforge.net/hibernate-mapping-3.0.dtd">

<hibernate-mapping>

	<class dynamic-insert="true" dynamic-update="true" name="nl.strohalm.cyclos.entities.members.messages.Message" table="messages">
		<id name="id" type="long">
			<column name="id" sql-type="integer"/>
			<generator class="native"/>
		</id>
		<property name="date" update="false" column="date" type="calendar" not-null="true" />
		<property name="subject" update="false" column="subject" type="string" not-null="true" />
        <property name="type" update="false" column="type" length="3" not-null="true">
            <type name="nl.strohalm.cyclos.utils.hibernate.StringValuedEnumType">
                <param name="enumClassName">nl.strohalm.cyclos.entities.members.messages.Message$Type</param>
            </type>
		</property>
        <property name="direction" update="false" column="direction" length="1" not-null="true">
            <type name="nl.strohalm.cyclos.utils.hibernate.StringValuedEnumType">
                <param name="enumClassName">nl.strohalm.cyclos.entities.members.messages.Message$Direction</param>
            </type>
		</property>
        <property name="read" column="is_read" not-null="true" type="boolean"/>
        <property name="replied" column="is_replied" not-null="true" type="boolean"/>
        <property name="html" column="is_html" not-null="true" type="boolean"/>
        <property name="removedAt" column="removed_at" type="calendar"/>
		<many-to-one name="fromMember" update="false" class="nl.strohalm.cyclos.entities.members.Member">
		    <column name="from_member_id" sql-type="integer"/>
		</many-to-one>
		<many-to-one name="toMember" update="false" class="nl.strohalm.cyclos.entities.members.Member">
		    <column name="to_member_id" sql-type="integer"/>
		</many-to-one>
		<many-to-one name="category" update="false" class="nl.strohalm.cyclos.entities.members.messages.MessageCategory">
		    <column name="category_id" sql-type="integer"/>
		</many-to-one>
		<property name="body" update="false" column="body" type="text" />
        <property name="emailSent" column="email_sent" not-null="true" type="boolean"/>
               	
		<bag name="toGroups" table="messages_to_groups">
			<key>
			    <column name="message_id" sql-type="integer"/>
			</key>
			<many-to-many class="nl.strohalm.cyclos.entities.groups.MemberGroup">
			    <column name="group_id" sql-type="integer"/>	
			</many-to-many>
		</bag>
	</class>

</hibernate-mapping>